MANIFEST.in
README.rst
setup.py
simula_bibrestclient/__init__.py
simula_bibrestclient/client.py
simula_bibrestclient/defaults.py
simula_bibrestclient/diff.py
simula_bibrestclient/mime.py
simula_bibrestclient/urllib2_request.py
simula_bibrestclient.egg-info/PKG-INFO
simula_bibrestclient.egg-info/SOURCES.txt
simula_bibrestclient.egg-info/dependency_links.txt
simula_bibrestclient.egg-info/entry_points.txt
simula_bibrestclient.egg-info/requires.txt
simula_bibrestclient.egg-info/top_level.txt
simula_bibrestclient.egg-info/zip-safe
simula_bibrestclient/cli/__init__.py
simula_bibrestclient/cli/argparse_for_oldpython.py
simula_bibrestclient/cli/argparseimport.py
simula_bibrestclient/cli/command.py
simula_bibrestclient/cli/main.py
simula_bibrestclient/cli/search.py
simula_bibrestclient/cli/update.py
simula_bibrestclient/cli/version.py
simula_bibrestclient/tests/__init__.py
simula_bibrestclient/tests/test_client.py