Metadata-Version: 1.0
Name: simula-bibrestclient
Version: 1.0.4
Summary: RESTful client for the Simula (http://simula.no) bibliography REST api.
Home-page: http://github.com/espenak/simula_bibrestclient
Author: Espen Angell Kristiansen
Author-email: post@espenak.net
License: BSD
Platform: UNKNOWN
Classifier: Development Status :: 5 - Production/Stable
Classifier: License :: OSI Approved
Classifier: Operating System :: OS Independent
Classifier: Programming Language :: Python
